examples/__init__.py
examples/autoencoder/DimensionalityReductionDemo.py
examples/autoencoder/IMDbWordEmbeddingDemo.py
examples/autoencoder/__init__.py
examples/classification/CIFAR2Demo3x3LiteralBudget.py
examples/classification/IMDbSparseAbsorbingTextCategorizationDemo.py
examples/classification/IMDbTextCategorizationDemo.py
examples/classification/InterpretabilityDemo.py
examples/classification/MNISTConvolutionDemo.py
examples/classification/MNISTDemo.py
examples/classification/MNISTDemoCoalesced.py
examples/classification/MNISTDemoWithSerialization.py
examples/classification/MNISTSparseAbsorbingDemo.py
examples/classification/XORDemo.py
examples/classification/__init__.py
examples/composite/TMCompositeCIFAR10Demo.py
examples/composite/__init__.py
examples/composite/hpsearch/__init__.py
examples/composite/hpsearch/example_2.py
examples/experimental/__init__.py
examples/experimental/autoencoder/IMDbAutoEncoderDemo.py
examples/experimental/autoencoder/MNISTReconstructionDemo.py
examples/experimental/autoencoder/NoiseRemovalDemo.py
examples/experimental/autoencoder/__init__.py
examples/experimental/classification/BillionWordsPredictionDemo.py
examples/experimental/classification/CIFAR100CoalescedDemo3x3.py
examples/experimental/classification/CIFAR100CoalescedDemo3x3LiteralBudget.py
examples/experimental/classification/CIFAR100Demo3x3.py
examples/experimental/classification/CIFAR100MultiTaskDemo3x3.py
examples/experimental/classification/CIFAR100MultiTaskSampleDemo3x3.py
examples/experimental/classification/CIFAR10CoalescedDemo.py
examples/experimental/classification/CIFAR10CoalescedDemo3x3.py
examples/experimental/classification/CIFAR10CoalescedDemo3x3LiteralBudget.py
examples/experimental/classification/CIFAR10Demo.py
examples/experimental/classification/CIFAR10DemoS.py
examples/experimental/classification/CIFAR10MultiTaskSampleDemo3x3.py
examples/experimental/classification/CIFAR2Demo3x3HSVLiteralBudget.py
tmu-0.8.3.dist-info/LICENSE
tmu-0.8.3.dist-info/METADATA
tmu-0.8.3.dist-info/WHEEL
tmu-0.8.3.dist-info/top_level.txt
tmu-0.8.3.dist-info/RECORD
