Metadata-Version: 2.1
Name: tmu
Version: 0.8.3
Summary: Your project description
Author-email: Ole-Christoffer Granmo <ole.granmo@uia.no>, Per-Arne Andersen <per.andersen@uia.no>
License: MIT License
Project-URL: homepage, https://github.com/cair/tmu/
Project-URL: repository, https://github.com/cair/tmu/
Requires-Python: >=3.10
License-File: LICENSE
Requires-Dist: cffi >=1.15.0
Requires-Dist: numpy
Requires-Dist: pandas
Requires-Dist: scikit-learn
Requires-Dist: tqdm
Requires-Dist: requests
Requires-Dist: xxhash
Provides-Extra: composite
Requires-Dist: opencv-python-headless ; extra == 'composite'
Requires-Dist: pydantic ; extra == 'composite'
Requires-Dist: optuna ; extra == 'composite'
Requires-Dist: joblib ; extra == 'composite'
Provides-Extra: examples
Requires-Dist: scikit-learn ; extra == 'examples'
Requires-Dist: tensorflow ; extra == 'examples'
Provides-Extra: tests
Requires-Dist: pytest ; extra == 'tests'
